{
  "sections": {
    "sidebar": {
      "type": "product-sidebar",
      "disabled": true,
      "settings": {
        "toggle": false
      }
    },
    "main": {
      "type": "product-template",
      "blocks": {
        "title": {
          "type": "title",
          "settings": {}
        },
        "price": {
          "type": "price",
          "settings": {
            "display_savings": true
          }
        },
        "form": {
          "type": "form",
          "settings": {
            "show_gift_card_recipient_form": false
          }
        },
        "description": {
          "type": "description",
          "settings": {}
        },
        "298d0e2c-a81a-416a-b198-5311b0ec49c7": {
          "type": "shopify:\/\/apps\/product-reviews\/blocks\/star_rating\/bae150af-8da8-48b2-9867-398188115e5f",
          "settings": {
            "stars_fill_color": "#000000",
            "star_size": 15,
            "text_align": "center",
            "product": "{{product}}",
            "stars_text_empty": "No hay comentarios"
          }
        },
        "ca56dfca-a368-41b4-9e45-8b7c865c8e29": {
          "type": "shopify:\/\/apps\/product-reviews\/blocks\/reviews\/bae150af-8da8-48b2-9867-398188115e5f",
          "settings": {}
        }
      },
      "block_order": [
        "title",
        "price",
        "form",
        "description",
        "298d0e2c-a81a-416a-b198-5311b0ec49c7",
        "ca56dfca-a368-41b4-9e45-8b7c865c8e29"
      ],
      "settings": {
        "product_breadcrumb": true,
        "media_position": "is-flex-row",
        "set_product_height": false,
        "product_height": 500,
        "video_looping": false,
        "product_thumbs": true,
        "gallery_arrows": false,
        "enable_product_lightbox": true,
        "activate_zoom": true,
        "slideshow_speed": 0,
        "slideshow_animation": "fade",
        "thumbnail_position": "right",
        "enable_thumbnail_slider": true
      }
    },
    "recently-viewed": {
      "type": "recently-viewed",
      "settings": {
        "rv_title": "Vistos recientemente",
        "rv_max_display": 4,
        "rv_per": 4,
        "css_class": "",
        "custom_css": ""
      }
    },
    "recommendations": {
      "type": "product-recommendations",
      "settings": {
        "show_product_recommendations": true,
        "wide_display": false,
        "product_recommendations_style": "grid",
        "product_recommendations_heading": "También te podrían interesar...",
        "products_per_row": 5,
        "recommended_products_limit": 5
      }
    },
    "newsletter": {
      "type": "newsletter",
      "disabled": true,
      "settings": {
        "wide_display": true,
        "display_first_name": false,
        "display_last_name": false,
        "newsletter_title": "Subscribe",
        "newsletter_text": "<p>Sign up to get the latest on sales, new releases and more …<\/p>",
        "newsletter_section_text_align": "center",
        "css_class": "",
        "custom_css": ""
      }
    }
  },
  "order": [
    "sidebar",
    "main",
    "recently-viewed",
    "recommendations",
    "newsletter"
  ]
}